qiskit_addon_mpf/__init__.py
qiskit_addon_mpf/dynamic.py
qiskit_addon_mpf/static.py
qiskit_addon_mpf/backends/__init__.py
qiskit_addon_mpf/backends/interface.py
qiskit_addon_mpf/backends/quimb_circuit/__init__.py
qiskit_addon_mpf/backends/quimb_circuit/evolver.py
qiskit_addon_mpf/backends/quimb_circuit/state.py
qiskit_addon_mpf/backends/quimb_layers/__init__.py
qiskit_addon_mpf/backends/quimb_layers/evolver.py
qiskit_addon_mpf/backends/quimb_layers/model.py
qiskit_addon_mpf/backends/quimb_tebd/__init__.py
qiskit_addon_mpf/backends/quimb_tebd/evolver.py
qiskit_addon_mpf/backends/quimb_tebd/state.py
qiskit_addon_mpf/backends/tenpy_layers/__init__.py
qiskit_addon_mpf/backends/tenpy_layers/evolver.py
qiskit_addon_mpf/backends/tenpy_layers/model.py
qiskit_addon_mpf/backends/tenpy_tebd/__init__.py
qiskit_addon_mpf/backends/tenpy_tebd/evolver.py
qiskit_addon_mpf/backends/tenpy_tebd/state.py
qiskit_addon_mpf/costs/__init__.py
qiskit_addon_mpf/costs/exact.py
qiskit_addon_mpf/costs/frobenius.py
qiskit_addon_mpf/costs/lse.py
qiskit_addon_mpf/costs/sum_of_squares.py
qiskit_addon_mpf-0.3.0.dist-info/METADATA
qiskit_addon_mpf-0.3.0.dist-info/WHEEL
qiskit_addon_mpf-0.3.0.dist-info/licenses/LICENSE.txt
qiskit_addon_mpf-0.3.0.dist-info/RECORD
