Metadata-Version: 2.4
Name: qiskit-addon-mpf
Version: 0.3.0
Summary: Reducing the Trotter error of Hamiltonian dynamics with multi-product formulas
License:                     Copyright 2024 IBM and its contributors
License-File: LICENSE.txt
Classifier: Intended Audience :: Developers
Classifier: Intended Audience :: Science/Research
Classifier: License :: OSI Approved :: Apache Software License
Classifier: Natural Language :: English
Classifier: Operating System :: MacOS
Classifier: Operating System :: Microsoft :: Windows
Classifier: Operating System :: POSIX :: Linux
Classifier: Programming Language :: Python :: 3.9
Classifier: Programming Language :: Python :: 3.10
Classifier: Programming Language :: Python :: 3.11
Classifier: Programming Language :: Python :: 3.12
Classifier: Programming Language :: Python :: 3.13
Classifier: Topic :: Scientific/Engineering :: Physics
Requires-Python: >=3.9
Requires-Dist: cvxpy>=1.6
Requires-Dist: numpy>=1.23
Requires-Dist: qiskit<3,>=1.2
Provides-Extra: basetest
Requires-Dist: physics-tenpy<2,>=1.0.4; extra == 'basetest'
Requires-Dist: pytest-cov>=5.0; extra == 'basetest'
Requires-Dist: pytest-subtests>=0.13; extra == 'basetest'
Requires-Dist: pytest>=8.0; extra == 'basetest'
Requires-Dist: qiskit-addon-utils; extra == 'basetest'
Requires-Dist: qiskit-quimb; extra == 'basetest'
Requires-Dist: quimb<2,>=1.10.0; extra == 'basetest'
Provides-Extra: dev
Requires-Dist: ipywidgets; extra == 'dev'
Requires-Dist: jupyter-sphinx; extra == 'dev'
Requires-Dist: matplotlib; extra == 'dev'
Requires-Dist: mypy==1.15.0; extra == 'dev'
Requires-Dist: nbmake>=1.5.0; extra == 'dev'
Requires-Dist: nbqa>=1.8.5; extra == 'dev'
Requires-Dist: nbsphinx>=0.9.4; extra == 'dev'
Requires-Dist: physics-tenpy<2,>=1.0.4; extra == 'dev'
Requires-Dist: pylatexenc; extra == 'dev'
Requires-Dist: pylint==3.3.4; extra == 'dev'
Requires-Dist: pytest-cov>=5.0; extra == 'dev'
Requires-Dist: pytest-doctestplus>=1.2.1; extra == 'dev'
Requires-Dist: pytest-subtests>=0.13; extra == 'dev'
Requires-Dist: pytest>=8.0; extra == 'dev'
Requires-Dist: qiskit-addon-utils; extra == 'dev'
Requires-Dist: qiskit-quimb; extra == 'dev'
Requires-Dist: qiskit-sphinx-theme~=2.0.0; extra == 'dev'
Requires-Dist: quimb<2,>=1.10.0; extra == 'dev'
Requires-Dist: reno>=4.1; extra == 'dev'
Requires-Dist: ruff==0.9.9; extra == 'dev'
Requires-Dist: rustworkx[graphviz]>=0.15; extra == 'dev'
Requires-Dist: sphinx-autodoc-typehints; extra == 'dev'
Requires-Dist: sphinx-copybutton; extra == 'dev'
Requires-Dist: sphinx-design; extra == 'dev'
Requires-Dist: sphinx-reredirects; extra == 'dev'
Requires-Dist: toml>=0.9.6; extra == 'dev'
Requires-Dist: tox>=4.4.3; extra == 'dev'
Requires-Dist: typos>=1.20.0; extra == 'dev'
Provides-Extra: docs
Requires-Dist: ipywidgets; extra == 'docs'
Requires-Dist: jupyter-sphinx; extra == 'docs'
Requires-Dist: matplotlib; extra == 'docs'
Requires-Dist: nbsphinx>=0.9.4; extra == 'docs'
Requires-Dist: physics-tenpy<2,>=1.0.4; extra == 'docs'
Requires-Dist: pylatexenc; extra == 'docs'
Requires-Dist: pytest-cov>=5.0; extra == 'docs'
Requires-Dist: pytest-doctestplus>=1.2.1; extra == 'docs'
Requires-Dist: pytest-subtests>=0.13; extra == 'docs'
Requires-Dist: pytest>=8.0; extra == 'docs'
Requires-Dist: qiskit-addon-utils; extra == 'docs'
Requires-Dist: qiskit-quimb; extra == 'docs'
Requires-Dist: qiskit-sphinx-theme~=2.0.0; extra == 'docs'
Requires-Dist: quimb<2,>=1.10.0; extra == 'docs'
Requires-Dist: reno>=4.1; extra == 'docs'
Requires-Dist: rustworkx[graphviz]>=0.15; extra == 'docs'
Requires-Dist: sphinx-autodoc-typehints; extra == 'docs'
Requires-Dist: sphinx-copybutton; extra == 'docs'
Requires-Dist: sphinx-design; extra == 'docs'
Requires-Dist: sphinx-reredirects; extra == 'docs'
Provides-Extra: doctest
Requires-Dist: ipywidgets; extra == 'doctest'
Requires-Dist: matplotlib; extra == 'doctest'
Requires-Dist: physics-tenpy<2,>=1.0.4; extra == 'doctest'
Requires-Dist: pylatexenc; extra == 'doctest'
Requires-Dist: pytest-cov>=5.0; extra == 'doctest'
Requires-Dist: pytest-doctestplus>=1.2.1; extra == 'doctest'
Requires-Dist: pytest-subtests>=0.13; extra == 'doctest'
Requires-Dist: pytest>=8.0; extra == 'doctest'
Requires-Dist: qiskit-addon-utils; extra == 'doctest'
Requires-Dist: qiskit-quimb; extra == 'doctest'
Requires-Dist: quimb<2,>=1.10.0; extra == 'doctest'
Requires-Dist: rustworkx[graphviz]>=0.15; extra == 'doctest'
Provides-Extra: dynamic
Requires-Dist: physics-tenpy<2,>=1.0.4; extra == 'dynamic'
Requires-Dist: qiskit-quimb; extra == 'dynamic'
Requires-Dist: quimb<2,>=1.10.0; extra == 'dynamic'
Provides-Extra: lint
Requires-Dist: mypy==1.15.0; extra == 'lint'
Requires-Dist: nbqa>=1.8.5; extra == 'lint'
Requires-Dist: pylint==3.3.4; extra == 'lint'
Requires-Dist: reno>=4.1; extra == 'lint'
Requires-Dist: ruff==0.9.9; extra == 'lint'
Requires-Dist: toml>=0.9.6; extra == 'lint'
Requires-Dist: typos>=1.20.0; extra == 'lint'
Provides-Extra: nbtest
Requires-Dist: nbmake>=1.5.0; extra == 'nbtest'
Requires-Dist: physics-tenpy<2,>=1.0.4; extra == 'nbtest'
Requires-Dist: pytest-cov>=5.0; extra == 'nbtest'
Requires-Dist: pytest-subtests>=0.13; extra == 'nbtest'
Requires-Dist: pytest>=8.0; extra == 'nbtest'
Requires-Dist: qiskit-addon-utils; extra == 'nbtest'
Requires-Dist: qiskit-quimb; extra == 'nbtest'
Requires-Dist: quimb<2,>=1.10.0; extra == 'nbtest'
Provides-Extra: notebook-dependencies
Requires-Dist: ipywidgets; extra == 'notebook-dependencies'
Requires-Dist: matplotlib; extra == 'notebook-dependencies'
Requires-Dist: pylatexenc; extra == 'notebook-dependencies'
Requires-Dist: rustworkx[graphviz]>=0.15; extra == 'notebook-dependencies'
Provides-Extra: quimb
Requires-Dist: qiskit-quimb; extra == 'quimb'
Requires-Dist: quimb<2,>=1.10.0; extra == 'quimb'
Provides-Extra: style
Requires-Dist: nbqa>=1.8.5; extra == 'style'
Requires-Dist: ruff==0.9.9; extra == 'style'
Requires-Dist: typos>=1.20.0; extra == 'style'
Provides-Extra: tenpy
Requires-Dist: physics-tenpy<2,>=1.0.4; extra == 'tenpy'
Provides-Extra: test
Requires-Dist: physics-tenpy<2,>=1.0.4; extra == 'test'
Requires-Dist: pytest-cov>=5.0; extra == 'test'
Requires-Dist: pytest-subtests>=0.13; extra == 'test'
Requires-Dist: pytest>=8.0; extra == 'test'
Requires-Dist: qiskit-addon-utils; extra == 'test'
Requires-Dist: qiskit-quimb; extra == 'test'
Requires-Dist: quimb<2,>=1.10.0; extra == 'test'
